coriolis/__init__.py
coriolis/__main__.py
coriolis/custom.mplstyle
coriolis/app/__init__.py
coriolis/app/app.py
coriolis/app/util/__init__.py
coriolis/app/util/extract.py
coriolis/app/util/refresh.py
coriolis/app/util/save.py
coriolis/app/util/viz.py
coriolis/app/widgets/__init__.py
coriolis/app/widgets/gboxes.py
coriolis/app/widgets/menu.py
coriolis/app/widgets/viz.py
coriolis/util/__init__.py
coriolis/util/analyze_dims.py
coriolis/util/code2text.py
coriolis/util/format.py
coriolis/util/postproc.py
coriolis/util/preproc.py
coriolis/util/style_sheet.py
coriolis-0.0.1.dist-info/LICENSE.txt
coriolis-0.0.1.dist-info/METADATA
coriolis-0.0.1.dist-info/WHEEL
coriolis-0.0.1.dist-info/entry_points.txt
coriolis-0.0.1.dist-info/top_level.txt
coriolis-0.0.1.dist-info/RECORD
