Metadata-Version: 2.1
Name: coriolis
Version: 0.0.1
Summary: Quick visualization python software for NetCDF files
Home-page: http://github.com/jthanwer/coriolis
Author: Joel Thanwerdas
Author-email: joel.thanwerdas@gmail.com
License: UNKNOWN
Platform: UNKNOWN
Classifier: Programming Language :: Python :: 3
Classifier: Development Status :: 3 - Alpha
Classifier: License :: OSI Approved :: GNU General Public License v3 (GPLv3)
Classifier: Natural Language :: English
Classifier: Operating System :: OS Independent
Classifier: Topic :: Scientific/Engineering :: Atmospheric Science
